<?xml version="1.0" encoding="utf-8"?>
<TextureAtlas imagePath="logoShine.png">
	<!-- Created with Adobe Animate version 22.0.3.179 -->
	<!-- http://www.adobe.com/products/animate.html -->
	<SubTexture name="logoShakelol0000" x="10" y="10" width="978" height="257" frameX="-599" frameY="-344" frameWidth="2177" frameHeight="946"/>
	<SubTexture name="logoShakelol0001" x="10" y="10" width="978" height="257" frameX="-599" frameY="-344" frameWidth="2177" frameHeight="946"/>
	<SubTexture name="logoShakelol0002" x="10" y="10" width="978" height="257" frameX="-599" frameY="-344" frameWidth="2177" frameHeight="946"/>
	<SubTexture name="logoShakelol0003" x="10" y="10" width="978" height="257" frameX="-599" frameY="-344" frameWidth="2177" frameHeight="946"/>
	<SubTexture name="logoShakelol0004" x="10" y="10" width="978" height="257" frameX="-599" frameY="-344" frameWidth="2177" frameHeight="946"/>
	<SubTexture name="logoShakelol0005" x="10" y="10" width="978" height="257" frameX="-599" frameY="-344" frameWidth="2177" frameHeight="946"/>
	<SubTexture name="logoShakelol0006" x="10" y="10" width="978" height="257" frameX="-599" frameY="-344" frameWidth="2177" frameHeight="946"/>
	<SubTexture name="logoShakelol0007" x="10" y="10" width="978" height="257" frameX="-599" frameY="-344" frameWidth="2177" frameHeight="946"/>
	<SubTexture name="logoShakelol0008" x="10" y="10" width="978" height="257" frameX="-599" frameY="-344" frameWidth="2177" frameHeight="946"/>
	<SubTexture name="logoShakelol0009" x="10" y="10" width="978" height="257" frameX="-599" frameY="-344" frameWidth="2177" frameHeight="946"/>
	<SubTexture name="logoShakelol0010" x="10" y="10" width="978" height="257" frameX="-599" frameY="-344" frameWidth="2177" frameHeight="946"/>
	<SubTexture name="logoShakelol0011" x="10" y="10" width="978" height="257" frameX="-599" frameY="-344" frameWidth="2177" frameHeight="946"/>
	<SubTexture name="logoShakelol0012" x="10" y="10" width="978" height="257" frameX="-599" frameY="-344" frameWidth="2177" frameHeight="946"/>
	<SubTexture name="logoShakelol0013" x="10" y="10" width="978" height="257" frameX="-599" frameY="-344" frameWidth="2177" frameHeight="946"/>
	<SubTexture name="logoShakelol0014" x="10" y="10" width="978" height="257" frameX="-599" frameY="-344" frameWidth="2177" frameHeight="946"/>
	<SubTexture name="logoShakelol0015" x="10" y="10" width="978" height="257" frameX="-599" frameY="-344" frameWidth="2177" frameHeight="946"/>
	<SubTexture name="logoShakelol0016" x="10" y="10" width="978" height="257" frameX="-599" frameY="-344" frameWidth="2177" frameHeight="946"/>
	<SubTexture name="logoShakelol0017" x="10" y="10" width="978" height="257" frameX="-599" frameY="-344" frameWidth="2177" frameHeight="946"/>
	<SubTexture name="logoShakelol0018" x="10" y="10" width="978" height="257" frameX="-599" frameY="-344" frameWidth="2177" frameHeight="946"/>
	<SubTexture name="logoShakelol0019" x="10" y="10" width="978" height="257" frameX="-575" frameY="-342" frameWidth="2177" frameHeight="946"/>
	<SubTexture name="logoShakelol0020" x="10" y="10" width="978" height="257" frameX="-571" frameY="-329" frameWidth="2177" frameHeight="946"/>
	<SubTexture name="logoShakelol0021" x="10" y="10" width="978" height="257" frameX="-587" frameY="-338" frameWidth="2177" frameHeight="946"/>
	<SubTexture name="logoShakelol0022" x="10" y="10" width="978" height="257" frameX="-595" frameY="-340" frameWidth="2177" frameHeight="946"/>
	<SubTexture name="logoShakelol0023" x="10" y="10" width="978" height="257" frameX="-599" frameY="-344" frameWidth="2177" frameHeight="946"/>
	<SubTexture name="logoShakelol0024" x="10" y="10" width="978" height="257" frameX="-601" frameY="-342" frameWidth="2177" frameHeight="946"/>
	<SubTexture name="logoShakelol0025" x="10" y="10" width="978" height="257" frameX="-599" frameY="-344" frameWidth="2177" frameHeight="946"/>
	<SubTexture name="logoShakelol0026" x="10" y="10" width="978" height="257" frameX="-599" frameY="-344" frameWidth="2177" frameHeight="946"/>
	<SubTexture name="logoShakelol0027" x="10" y="10" width="978" height="257" frameX="-599" frameY="-344" frameWidth="2177" frameHeight="946"/>
	<SubTexture name="logoShakelol0028" x="10" y="10" width="978" height="257" frameX="-599" frameY="-344" frameWidth="2177" frameHeight="946"/>
	<SubTexture name="logoShakelol0029" x="10" y="10" width="978" height="257" frameX="-599" frameY="-344" frameWidth="2177" frameHeight="946"/>
	<SubTexture name="logoShakelol0030" x="10" y="10" width="978" height="257" frameX="-599" frameY="-344" frameWidth="2177" frameHeight="946"/>
	<SubTexture name="logoShakelol0031" x="10" y="10" width="978" height="257" frameX="-599" frameY="-344" frameWidth="2177" frameHeight="946"/>
	<SubTexture name="logoShakelol0032" x="10" y="10" width="978" height="257" frameX="-599" frameY="-344" frameWidth="2177" frameHeight="946"/>
	<SubTexture name="logoShakelol0033" x="10" y="10" width="978" height="257" frameX="-599" frameY="-344" frameWidth="2177" frameHeight="946"/>
	<SubTexture name="logoShakelol0034" x="10" y="10" width="978" height="257" frameX="-575" frameY="-342" frameWidth="2177" frameHeight="946"/>
	<SubTexture name="logoShakelol0035" x="10" y="10" width="978" height="257" frameX="-571" frameY="-329" frameWidth="2177" frameHeight="946"/>
	<SubTexture name="logoShakelol0036" x="10" y="10" width="978" height="257" frameX="-587" frameY="-338" frameWidth="2177" frameHeight="946"/>
	<SubTexture name="logoShakelol0037" x="10" y="10" width="978" height="257" frameX="-595" frameY="-340" frameWidth="2177" frameHeight="946"/>
	<SubTexture name="logoShakelol0038" x="10" y="10" width="978" height="257" frameX="-599" frameY="-344" frameWidth="2177" frameHeight="946"/>
	<SubTexture name="logoShakelol0039" x="10" y="10" width="978" height="257" frameX="-601" frameY="-342" frameWidth="2177" frameHeight="946"/>
	<SubTexture name="logoShakelol0040" x="10" y="10" width="978" height="257" frameX="-599" frameY="-344" frameWidth="2177" frameHeight="946"/>
	<SubTexture name="logoShakelol0041" x="10" y="10" width="978" height="257" frameX="-599" frameY="-344" frameWidth="2177" frameHeight="946"/>
	<SubTexture name="logoShakelol0042" x="10" y="10" width="978" height="257" frameX="-599" frameY="-344" frameWidth="2177" frameHeight="946"/>
	<SubTexture name="logoShakelol0043" x="10" y="10" width="978" height="257" frameX="-599" frameY="-344" frameWidth="2177" frameHeight="946"/>
	<SubTexture name="logoShakelol0044" x="10" y="10" width="978" height="257" frameX="-599" frameY="-344" frameWidth="2177" frameHeight="946"/>
	<SubTexture name="logoShakelol0045" x="10" y="10" width="978" height="257" frameX="-599" frameY="-344" frameWidth="2177" frameHeight="946"/>
	<SubTexture name="logoShakelol0046" x="10" y="10" width="978" height="257" frameX="-599" frameY="-344" frameWidth="2177" frameHeight="946"/>
	<SubTexture name="logoShakelol0047" x="10" y="10" width="978" height="257" frameX="-599" frameY="-344" frameWidth="2177" frameHeight="946"/>
	<SubTexture name="logoShakelol0048" x="10" y="10" width="978" height="257" frameX="-599" frameY="-344" frameWidth="2177" frameHeight="946"/>
	<SubTexture name="logoShakelol0049" x="10" y="10" width="978" height="257" frameX="-599" frameY="-344" frameWidth="2177" frameHeight="946"/>
	<SubTexture name="logoShakelol0050" x="10" y="10" width="978" height="257" frameX="-599" frameY="-344" frameWidth="2177" frameHeight="946"/>
	<SubTexture name="logoShakelol0051" x="10" y="10" width="978" height="257" frameX="-599" frameY="-344" frameWidth="2177" frameHeight="946"/>
	<SubTexture name="logoShakelol0052" x="10" y="10" width="978" height="257" frameX="-599" frameY="-344" frameWidth="2177" frameHeight="946"/>
	<SubTexture name="logoShakelol0053" x="10" y="10" width="978" height="257" frameX="-599" frameY="-344" frameWidth="2177" frameHeight="946"/>
	<SubTexture name="logoShakelol0054" x="10" y="10" width="978" height="257" frameX="-575" frameY="-342" frameWidth="2177" frameHeight="946"/>
	<SubTexture name="logoShakelol0055" x="10" y="10" width="978" height="257" frameX="-571" frameY="-329" frameWidth="2177" frameHeight="946"/>
	<SubTexture name="logoShakelol0056" x="10" y="10" width="978" height="257" frameX="-587" frameY="-338" frameWidth="2177" frameHeight="946"/>
	<SubTexture name="logoShakelol0057" x="10" y="10" width="978" height="257" frameX="-595" frameY="-340" frameWidth="2177" frameHeight="946"/>
	<SubTexture name="logoShakelol0058" x="10" y="10" width="978" height="257" frameX="-599" frameY="-344" frameWidth="2177" frameHeight="946"/>
	<SubTexture name="logoShakelol0059" x="10" y="10" width="978" height="257" frameX="-601" frameY="-342" frameWidth="2177" frameHeight="946"/>
	<SubTexture name="logoShakelol0060" x="10" y="10" width="978" height="257" frameX="-599" frameY="-344" frameWidth="2177" frameHeight="946"/>
	<SubTexture name="logoShakelol0061" x="10" y="10" width="978" height="257" frameX="-599" frameY="-344" frameWidth="2177" frameHeight="946"/>
	<SubTexture name="logoShakelol0062" x="10" y="10" width="978" height="257" frameX="-599" frameY="-344" frameWidth="2177" frameHeight="946"/>
	<SubTexture name="logoShakelol0063" x="10" y="10" width="978" height="257" frameX="-599" frameY="-344" frameWidth="2177" frameHeight="946"/>
	<SubTexture name="logoShakelol0064" x="10" y="10" width="978" height="257" frameX="-599" frameY="-344" frameWidth="2177" frameHeight="946"/>
	<SubTexture name="logoShakelol0065" x="10" y="10" width="978" height="257" frameX="-599" frameY="-344" frameWidth="2177" frameHeight="946"/>
	<SubTexture name="logoShakelol0066" x="10" y="10" width="978" height="257" frameX="-599" frameY="-344" frameWidth="2177" frameHeight="946"/>
	<SubTexture name="logoShakelol0067" x="10" y="10" width="978" height="257" frameX="-599" frameY="-344" frameWidth="2177" frameHeight="946"/>
	<SubTexture name="logoShakelol0068" x="10" y="10" width="978" height="257" frameX="-599" frameY="-344" frameWidth="2177" frameHeight="946"/>
	<SubTexture name="logoShakelol0069" x="10" y="10" width="978" height="257" frameX="-599" frameY="-344" frameWidth="2177" frameHeight="946"/>
	<SubTexture name="logoShakelol0070" x="10" y="10" width="978" height="257" frameX="-599" frameY="-344" frameWidth="2177" frameHeight="946"/>
	<SubTexture name="logoShakelol0071" x="10" y="10" width="978" height="257" frameX="-599" frameY="-344" frameWidth="2177" frameHeight="946"/>
	<SubTexture name="logoShakelol0072" x="10" y="10" width="978" height="257" frameX="-599" frameY="-344" frameWidth="2177" frameHeight="946"/>
	<SubTexture name="logoShakelol0073" x="10" y="10" width="978" height="257" frameX="-599" frameY="-344" frameWidth="2177" frameHeight="946"/>
	<SubTexture name="logoShakelol0074" x="10" y="10" width="978" height="257" frameX="-599" frameY="-344" frameWidth="2177" frameHeight="946"/>
	<SubTexture name="logoShakelol0075" x="10" y="10" width="978" height="257" frameX="-599" frameY="-344" frameWidth="2177" frameHeight="946"/>
	<SubTexture name="logoShakelol0076" x="10" y="10" width="978" height="257" frameX="-599" frameY="-344" frameWidth="2177" frameHeight="946"/>
	<SubTexture name="logoShakelol0077" x="10" y="10" width="978" height="257" frameX="-599" frameY="-344" frameWidth="2177" frameHeight="946"/>
	<SubTexture name="logoShakelol0078" x="10" y="10" width="978" height="257" frameX="-599" frameY="-344" frameWidth="2177" frameHeight="946"/>
	<SubTexture name="logoShakelol0079" x="998" y="10" width="978" height="257" frameX="-599" frameY="-344" frameWidth="2177" frameHeight="946"/>
	<SubTexture name="logoShakelol0080" x="1986" y="10" width="978" height="257" frameX="-599" frameY="-344" frameWidth="2177" frameHeight="946"/>
	<SubTexture name="logoShakelol0081" x="2974" y="10" width="978" height="257" frameX="-599" frameY="-344" frameWidth="2177" frameHeight="946"/>
	<SubTexture name="logoShakelol0082" x="3962" y="10" width="2177" height="946"/>
	<SubTexture name="logoShakelol0083" x="10" y="966" width="2115" height="910" frameX="-31" frameY="-18" frameWidth="2177" frameHeight="946"/>
	<SubTexture name="logoShakelol0084" x="2135" y="966" width="2021" height="856" frameX="-78" frameY="-45" frameWidth="2177" frameHeight="946"/>
	<SubTexture name="logoShakelol0085" x="4166" y="966" width="1843" height="754" frameX="-167" frameY="-96" frameWidth="2177" frameHeight="946"/>
	<SubTexture name="logoShakelol0086" x="6019" y="966" width="1497" height="556" frameX="-340" frameY="-195" frameWidth="2177" frameHeight="946"/>
	<SubTexture name="logoShakelol0087" x="10" y="1886" width="1295" height="441" frameX="-441" frameY="-252" frameWidth="2177" frameHeight="946"/>
	<SubTexture name="logoShakelol0088" x="1315" y="1886" width="1192" height="381" frameX="-492" frameY="-282" frameWidth="2177" frameHeight="946"/>
	<SubTexture name="logoShakelol0089" x="2517" y="1886" width="1126" height="343" frameX="-525" frameY="-301" frameWidth="2177" frameHeight="946"/>
	<SubTexture name="logoShakelol0090" x="3653" y="1886" width="1076" height="315" frameX="-550" frameY="-315" frameWidth="2177" frameHeight="946"/>
	<SubTexture name="logoShakelol0091" x="4739" y="1886" width="1042" height="295" frameX="-567" frameY="-325" frameWidth="2177" frameHeight="946"/>
	<SubTexture name="logoShakelol0092" x="5791" y="1886" width="1014" height="279" frameX="-581" frameY="-333" frameWidth="2177" frameHeight="946"/>
	<SubTexture name="logoShakelol0093" x="6815" y="1886" width="994" height="267" frameX="-591" frameY="-339" frameWidth="2177" frameHeight="946"/>
	<SubTexture name="logoShakelol0094" x="10" y="2337" width="1240" height="518" frameX="-468" frameY="-214" frameWidth="2177" frameHeight="946"/>
	<SubTexture name="logoShakelol0095" x="1260" y="2337" width="1180" height="459" frameX="-498" frameY="-243" frameWidth="2177" frameHeight="946"/>
	<SubTexture name="logoShakelol0096" x="2450" y="2337" width="1126" height="405" frameX="-525" frameY="-270" frameWidth="2177" frameHeight="946"/>
	<SubTexture name="logoShakelol0097" x="3586" y="2337" width="1082" height="361" frameX="-547" frameY="-292" frameWidth="2177" frameHeight="946"/>
	<SubTexture name="logoShakelol0098" x="4678" y="2337" width="1044" height="323" frameX="-566" frameY="-311" frameWidth="2177" frameHeight="946"/>
	<SubTexture name="logoShakelol0099" x="5732" y="2337" width="1016" height="295" frameX="-580" frameY="-325" frameWidth="2177" frameHeight="946"/>
	<SubTexture name="logoShakelol0100" x="6758" y="2337" width="996" height="275" frameX="-590" frameY="-335" frameWidth="2177" frameHeight="946"/>
	<SubTexture name="logoShakelol0101" x="10" y="2865" width="984" height="263" frameX="-596" frameY="-341" frameWidth="2177" frameHeight="946"/>
	<SubTexture name="logoShakelol0102" x="1004" y="2865" width="978" height="257" frameX="-599" frameY="-344" frameWidth="2177" frameHeight="946"/>
	<SubTexture name="logoShakelol0103" x="1004" y="2865" width="978" height="257" frameX="-599" frameY="-344" frameWidth="2177" frameHeight="946"/>
	<SubTexture name="logoShakelol0104" x="1004" y="2865" width="978" height="257" frameX="-599" frameY="-344" frameWidth="2177" frameHeight="946"/>
	<SubTexture name="logoShakelol0105" x="1004" y="2865" width="978" height="257" frameX="-599" frameY="-344" frameWidth="2177" frameHeight="946"/>
	<SubTexture name="logoShakelol0106" x="1004" y="2865" width="978" height="257" frameX="-599" frameY="-344" frameWidth="2177" frameHeight="946"/>
	<SubTexture name="logoShakelol0107" x="1004" y="2865" width="978" height="257" frameX="-599" frameY="-344" frameWidth="2177" frameHeight="946"/>
	<SubTexture name="logoShakelol0108" x="1004" y="2865" width="978" height="257" frameX="-599" frameY="-344" frameWidth="2177" frameHeight="946"/>
	<SubTexture name="logoShakelol0109" x="1004" y="2865" width="978" height="257" frameX="-599" frameY="-344" frameWidth="2177" frameHeight="946"/>
	<SubTexture name="logoShakelol0110" x="1004" y="2865" width="978" height="257" frameX="-599" frameY="-344" frameWidth="2177" frameHeight="946"/>
	<SubTexture name="logoShakelol0111" x="1004" y="2865" width="978" height="257" frameX="-599" frameY="-344" frameWidth="2177" frameHeight="946"/>
	<SubTexture name="logoShakelol0112" x="1004" y="2865" width="978" height="257" frameX="-599" frameY="-344" frameWidth="2177" frameHeight="946"/>
	<SubTexture name="logoShakelol0113" x="1004" y="2865" width="978" height="257" frameX="-599" frameY="-344" frameWidth="2177" frameHeight="946"/>
	<SubTexture name="logoShakelol0114" x="1004" y="2865" width="978" height="257" frameX="-599" frameY="-344" frameWidth="2177" frameHeight="946"/>
	<SubTexture name="logoShakelol0115" x="1004" y="2865" width="978" height="257" frameX="-599" frameY="-344" frameWidth="2177" frameHeight="946"/>
	<SubTexture name="logoShakelol0116" x="1004" y="2865" width="978" height="257" frameX="-599" frameY="-344" frameWidth="2177" frameHeight="946"/>
	<SubTexture name="logoShakelol0117" x="1004" y="2865" width="978" height="257" frameX="-599" frameY="-344" frameWidth="2177" frameHeight="946"/>
	<SubTexture name="logoShakelol0118" x="1004" y="2865" width="978" height="257" frameX="-599" frameY="-344" frameWidth="2177" frameHeight="946"/>
	<SubTexture name="logoShakelol0119" x="1004" y="2865" width="978" height="257" frameX="-599" frameY="-344" frameWidth="2177" frameHeight="946"/>
	<SubTexture name="logoShakelol0120" x="1004" y="2865" width="978" height="257" frameX="-599" frameY="-344" frameWidth="2177" frameHeight="946"/>
	<SubTexture name="logoShakelol0121" x="1004" y="2865" width="978" height="257" frameX="-599" frameY="-344" frameWidth="2177" frameHeight="946"/>
	<SubTexture name="logoShakelol0122" x="1004" y="2865" width="978" height="257" frameX="-599" frameY="-344" frameWidth="2177" frameHeight="946"/>
	<SubTexture name="logoShakelol0123" x="1004" y="2865" width="978" height="257" frameX="-599" frameY="-344" frameWidth="2177" frameHeight="946"/>
	<SubTexture name="logoShakelol0124" x="1004" y="2865" width="978" height="257" frameX="-599" frameY="-344" frameWidth="2177" frameHeight="946"/>
	<SubTexture name="logoShakelol0125" x="1004" y="2865" width="978" height="257" frameX="-599" frameY="-344" frameWidth="2177" frameHeight="946"/>
	<SubTexture name="logoShakelol0126" x="1004" y="2865" width="978" height="257" frameX="-599" frameY="-344" frameWidth="2177" frameHeight="946"/>
	<SubTexture name="logoShakelol0127" x="1004" y="2865" width="978" height="257" frameX="-599" frameY="-344" frameWidth="2177" frameHeight="946"/>
	<SubTexture name="logoShakelol0128" x="1004" y="2865" width="978" height="257" frameX="-599" frameY="-344" frameWidth="2177" frameHeight="946"/>
	<SubTexture name="logoShakelol0129" x="1004" y="2865" width="978" height="257" frameX="-599" frameY="-344" frameWidth="2177" frameHeight="946"/>
	<SubTexture name="logoShakelol0130" x="1004" y="2865" width="978" height="257" frameX="-599" frameY="-344" frameWidth="2177" frameHeight="946"/>
	<SubTexture name="logoShakelol0131" x="1004" y="2865" width="978" height="257" frameX="-599" frameY="-344" frameWidth="2177" frameHeight="946"/>
	<SubTexture name="logoShakelol0132" x="1004" y="2865" width="978" height="257" frameX="-599" frameY="-344" frameWidth="2177" frameHeight="946"/>
	<SubTexture name="logoShakelol0133" x="1004" y="2865" width="978" height="257" frameX="-599" frameY="-344" frameWidth="2177" frameHeight="946"/>
	<SubTexture name="logoShakelol0134" x="1004" y="2865" width="978" height="257" frameX="-599" frameY="-344" frameWidth="2177" frameHeight="946"/>
	<SubTexture name="logoShakelol0135" x="1004" y="2865" width="978" height="257" frameX="-599" frameY="-344" frameWidth="2177" frameHeight="946"/>
	<SubTexture name="logoShakelol0136" x="1004" y="2865" width="978" height="257" frameX="-599" frameY="-344" frameWidth="2177" frameHeight="946"/>
	<SubTexture name="logoShakelol0137" x="1004" y="2865" width="978" height="257" frameX="-599" frameY="-344" frameWidth="2177" frameHeight="946"/>
	<SubTexture name="logoShakelol0138" x="1004" y="2865" width="978" height="257" frameX="-599" frameY="-344" frameWidth="2177" frameHeight="946"/>
	<SubTexture name="logoShakelol0139" x="1004" y="2865" width="978" height="257" frameX="-599" frameY="-344" frameWidth="2177" frameHeight="946"/>
	<SubTexture name="logoShakelol0140" x="1004" y="2865" width="978" height="257" frameX="-599" frameY="-344" frameWidth="2177" frameHeight="946"/>
	<SubTexture name="logoShakelol0141" x="1004" y="2865" width="978" height="257" frameX="-599" frameY="-344" frameWidth="2177" frameHeight="946"/>
	<SubTexture name="logoShakelol0142" x="1004" y="2865" width="978" height="257" frameX="-599" frameY="-344" frameWidth="2177" frameHeight="946"/>
	<SubTexture name="logoShakelol0143" x="1004" y="2865" width="978" height="257" frameX="-599" frameY="-344" frameWidth="2177" frameHeight="946"/>
	<SubTexture name="logoShakelol0144" x="1004" y="2865" width="978" height="257" frameX="-599" frameY="-344" frameWidth="2177" frameHeight="946"/>
	<SubTexture name="logoShakelol0145" x="1004" y="2865" width="978" height="257" frameX="-599" frameY="-344" frameWidth="2177" frameHeight="946"/>
	<SubTexture name="logoShakelol0146" x="1004" y="2865" width="978" height="257" frameX="-599" frameY="-344" frameWidth="2177" frameHeight="946"/>
	<SubTexture name="logoShakelol0147" x="1004" y="2865" width="978" height="257" frameX="-599" frameY="-344" frameWidth="2177" frameHeight="946"/>
	<SubTexture name="logoShakelol0148" x="1004" y="2865" width="978" height="257" frameX="-599" frameY="-344" frameWidth="2177" frameHeight="946"/>
	<SubTexture name="logoShakelol0149" x="1004" y="2865" width="978" height="257" frameX="-599" frameY="-344" frameWidth="2177" frameHeight="946"/>
	<SubTexture name="logoShakelol0150" x="1004" y="2865" width="978" height="257" frameX="-599" frameY="-344" frameWidth="2177" frameHeight="946"/>
	<SubTexture name="logoShakelol0151" x="1004" y="2865" width="978" height="257" frameX="-599" frameY="-344" frameWidth="2177" frameHeight="946"/>
	<SubTexture name="logoShakelol0152" x="1004" y="2865" width="978" height="257" frameX="-599" frameY="-344" frameWidth="2177" frameHeight="946"/>
	<SubTexture name="logoShakelol0153" x="1004" y="2865" width="978" height="257" frameX="-599" frameY="-344" frameWidth="2177" frameHeight="946"/>
	<SubTexture name="logoShakelol0154" x="1004" y="2865" width="978" height="257" frameX="-599" frameY="-344" frameWidth="2177" frameHeight="946"/>
	<SubTexture name="logoShakelol0155" x="1004" y="2865" width="978" height="257" frameX="-599" frameY="-344" frameWidth="2177" frameHeight="946"/>
	<SubTexture name="logoShakelol0156" x="1004" y="2865" width="978" height="257" frameX="-599" frameY="-344" frameWidth="2177" frameHeight="946"/>
	<SubTexture name="logoShakelol0157" x="1004" y="2865" width="978" height="257" frameX="-599" frameY="-344" frameWidth="2177" frameHeight="946"/>
	<SubTexture name="logoShakelol0158" x="1004" y="2865" width="978" height="257" frameX="-599" frameY="-344" frameWidth="2177" frameHeight="946"/>
	<SubTexture name="logoShakelol0159" x="1004" y="2865" width="978" height="257" frameX="-599" frameY="-344" frameWidth="2177" frameHeight="946"/>
	<SubTexture name="logoShakelol0160" x="1004" y="2865" width="978" height="257" frameX="-599" frameY="-344" frameWidth="2177" frameHeight="946"/>
	<SubTexture name="logoShakelol0161" x="1004" y="2865" width="978" height="257" frameX="-599" frameY="-344" frameWidth="2177" frameHeight="946"/>
	<SubTexture name="logoShakelol0162" x="1004" y="2865" width="978" height="257" frameX="-599" frameY="-344" frameWidth="2177" frameHeight="946"/>
	<SubTexture name="logoShakelol0163" x="1004" y="2865" width="978" height="257" frameX="-599" frameY="-344" frameWidth="2177" frameHeight="946"/>
	<SubTexture name="logoShakelol0164" x="1004" y="2865" width="978" height="257" frameX="-599" frameY="-344" frameWidth="2177" frameHeight="946"/>
	<SubTexture name="logoShakelol0165" x="1004" y="2865" width="978" height="257" frameX="-599" frameY="-344" frameWidth="2177" frameHeight="946"/>
	<SubTexture name="logoShakelol0166" x="1004" y="2865" width="978" height="257" frameX="-599" frameY="-344" frameWidth="2177" frameHeight="946"/>
	<SubTexture name="logoShakelol0167" x="1004" y="2865" width="978" height="257" frameX="-599" frameY="-344" frameWidth="2177" frameHeight="946"/>
	<SubTexture name="logoShakelol0168" x="1004" y="2865" width="978" height="257" frameX="-599" frameY="-344" frameWidth="2177" frameHeight="946"/>
	<SubTexture name="logoShakelol0169" x="1004" y="2865" width="978" height="257" frameX="-599" frameY="-344" frameWidth="2177" frameHeight="946"/>
	<SubTexture name="logoShakelol0170" x="1004" y="2865" width="978" height="257" frameX="-599" frameY="-344" frameWidth="2177" frameHeight="946"/>
</TextureAtlas>
